encoding/encode.py
Encod-0.0.7.dist-info/LICENSE
Encod-0.0.7.dist-info/METADATA
Encod-0.0.7.dist-info/WHEEL
Encod-0.0.7.dist-info/top_level.txt
Encod-0.0.7.dist-info/RECORD
