Metadata-Version: 2.1
Name: Encod
Version: 0.0.7
Summary: A Python package to encode and decode with style.
Home-page: https://github.com/pisslow/styleEncoder/
Author: pisslow
Author-email: pisslowmail@gmail.com
License: MIT
Platform: UNKNOWN
